offiaccount/__init__.py
offiaccount/base/__init__.py
offiaccount/base/api.py
offiaccount/base/tokenizer.py
offiaccount/draft/__init__.py
offiaccount/draft/api.py
offiaccount/material/__init__.py
offiaccount/material/api.py
offiaccount/publish/__init__.py
offiaccount/publish/api.py
offiaccount/sendall/__init__.py
offiaccount/sendall/api.py
offiaccount-0.0.9.dist-info/LICENSE
offiaccount-0.0.9.dist-info/METADATA
offiaccount-0.0.9.dist-info/WHEEL
offiaccount-0.0.9.dist-info/top_level.txt
offiaccount-0.0.9.dist-info/RECORD
