Metadata-Version: 2.1
Name: offiaccount
Version: 0.0.9
Summary: WeChat Official Account API
Home-page: https://github.com/JiauZhang/offiaccount
Author: JiauZhang
Author-email: jiauzhang@163.com
License: GPL-2.0
Keywords: WeChat,Official Account,WeChat API
Classifier: Intended Audience :: Developers
Classifier: License :: OSI Approved :: GNU General Public License v2 (GPLv2)
Classifier: Programming Language :: Python :: 3.8
License-File: LICENSE
Requires-Dist: httpx
